pepedpid-0.1.1.dist-info/METADATA
pepedpid-0.1.1.dist-info/WHEEL
pepedpid-0.1.1.dist-info/licenses/LICENSE
pepedpid/__init__.py
pepedpid/__init__.pyi
pepedpid/py.typed
pepedpid/pepedpid.cpython-311-powerpc64le-linux-gnu.so
pepedpid-0.1.1.dist-info/RECORD
