Metadata-Version: 2.4
Name: pepedpid
Version: 0.1.1
Classifier: Programming Language :: Rust
Classifier: Programming Language :: Python :: Implementation :: CPython
Classifier: Programming Language :: Python :: Implementation :: PyPy
Requires-Dist: numpy
License-File: LICENSE
Requires-Python: >=3.8
